<?xml version="1.0" encoding="UTF-8" standalone="no"?>
<users>
    <user active="true">
        <email>dboyzetown@gmail.com</email>
        <userName>james</userName>
        <GUID>1711566d-f3f0-4cce-ba9d-341c33531088</GUID>
        <linkedMachines>
            <machine>7c9936bb-59e6-451b-a6fd-37340bbaabf5</machine>
        </linkedMachines>
    </user>
    <user>
        <email>inactive@gmail.com</email>
        <userName>inactive</userName>
        <GUID>650484e5-8fa0-497e-a545-9e416ed3bc2e</GUID>
        <linkedMachines>
            <machine>7c9936bb-59e6-451b-a6fd-37340bbaabf5</machine>
        </linkedMachines>
    </user>
</users>
